jstream/__init__.py
jstream/collectors.py
jstream/jstream.py
jstream-0.5.dist-info/LICENSE
jstream-0.5.dist-info/METADATA
jstream-0.5.dist-info/WHEEL
jstream-0.5.dist-info/top_level.txt
jstream-0.5.dist-info/RECORD
