Metadata-Version: 2.1
Name: jstream
Version: 0.5
Summary: Simple stream tool like java
Home-page: https://github.com/github-yxb/jstream
Author: yuanxb
Author-email: 
Classifier: Programming Language :: Python :: 3
Classifier: License :: OSI Approved :: MIT License
Classifier: Operating System :: OS Independent
Requires-Python: >=3.10
License-File: LICENSE
